plugypy/__init__.py
plugypy/configuration.py
plugypy/configuration_deserializer.py
plugypy/plugin.py
plugypy/plugin_manager.py
plugypy/plugypy_errors.py
PlugyPy-1.2.2.dist-info/LICENSE
PlugyPy-1.2.2.dist-info/METADATA
PlugyPy-1.2.2.dist-info/WHEEL
PlugyPy-1.2.2.dist-info/top_level.txt
PlugyPy-1.2.2.dist-info/RECORD
