Metadata-Version: 2.1
Name: PlugyPy
Version: 1.2.2
Summary: A lightweigh Python plugin system
Home-page: https://github.com/not-so-cool-anymore/plugypy
Author: Ivan Zlatanov
Author-email: i_zlatanov@protonmail.com
License: UNKNOWN
Platform: UNKNOWN
Classifier: Programming Language :: Python :: 3
Classifier: License :: OSI Approved :: GNU General Public License v3 or later (GPLv3+)
Classifier: Operating System :: OS Independent
Requires-Python: >=3.4
